{"took": 16, "timed_out": false, "_shards": {"total": 4, "successful": 4, "skipped": 0, "failed": 0}, "hits": {"total": {"value": 20, "relation": "eq"}, "max_score": 1.0, "hits": [{"_index": "amoscore", "_id": "lLpyPogBp1nEdZNQF7bH", "_score": 1.0, "_source": {"FileName": "image-00014.dcm", "FileSize": "92036", "MIMEType": "application/dicom", "FileInodeChangeDate": "2023-03-10 08:28:00", "SourceFile": "/media/harvest/domain/medical_science/dicom/series-00000/image-00014.dcm"}}, {"_index": "amoscore", "_id": "BuyjPogB9qMRW8nefvRq", "_score": 1.0, "_source": {"FileName": "image-00014.dcm", "FileSize": "92036", "MIMEType": "application/dicom", "FileInodeChangeDate": "2023-03-10 08:28:00", "SourceFile": "/media/harvest/domain/medical_science/dicom/series-00000/image-00014.dcm"}}, {"_index": "amoscore", "_id": "B-yjPogB9qMRW8nefvSM", "_score": 1.0, "_source": {"FileName": "image-00338.dcm", "FileSize": "95730", "MIMEType": "application/dicom", "FileInodeChangeDate": "2023-03-10 08:28:00", "SourceFile": "/media/harvest/domain/medical_science/dicom/series-00000/image-00338.dcm"}}, {"_index": "amoscore", "_id": "eYvZPogBB6yI3k9V5xYp", "_score": 1.0, "_source": {"FileName": "image-00338.dcm", "FileSize": "95730", "MIMEType": "application/dicom", "FileInodeChangeDate": "2023-03-10 08:28:00", "SourceFile": "/media/harvest/domain/medical_science/dicom/series-00000/image-00338.dcm"}}, {"_index": "amoscore", "_id": "zWTbPogBmAXtQgDo5csW", "_score": 1.0, "_source": {"FileName": "image-00041.dcm", "FileSize": "86664", "MIMEType": "application/dicom", "FileInodeChangeDate": "2023-03-10 08:28:00", "SourceFile": "/media/harvest/domain/medical_science/dicom/series-00000/image-00041.dcm"}}, {"_index": "amoscore", "_id": "krpyPogBp1nEdZNQDrYS", "_score": 1.0, "_source": {"FileName": "image-00041.dcm", "FileSize": "86664", "MIMEType": "application/dicom", "FileInodeChangeDate": "2023-03-10 08:28:00", "SourceFile": "/media/harvest/domain/medical_science/dicom/series-00000/image-00041.dcm"}}, {"_index": "amoscore", "_id": "dovZPogBB6yI3k9V5hZE", "_score": 1.0, "_source": {"FileName": "image-00041.dcm", "FileSize": "86664", "MIMEType": "application/dicom", "FileInodeChangeDate": "2023-03-10 08:28:00", "SourceFile": "/media/harvest/domain/medical_science/dicom/series-00000/image-00041.dcm"}}, {"_index": "amoscore", "_id": "d4vZPogBB6yI3k9V5hbd", "_score": 1.0, "_source": {"FileName": "image-00171.dcm", "FileSize": "92528", "MIMEType": "application/dicom", "FileInodeChangeDate": "2023-03-10 08:28:00", "SourceFile": "/media/harvest/domain/medical_science/dicom/series-00000/image-00171.dcm"}}, {"_index": "amoscore", "_id": "onE9RIgBPwy-eBciwYid", "_score": 1.0, "_source": {"FileName": "image-00041.dcm", "FileSize": "86664", "MIMEType": "application/dicom", "FileInodeChangeDate": "2023-03-10 08:28:00", "SourceFile": "/media/harvest/domain/medical_science/dicom/series-00000/image-00041.dcm"}}, {"_index": "amoscore", "_id": "eIvZPogBB6yI3k9V5xYI", "_score": 1.0, "_source": {"FileName": "image-00014.dcm", "FileSize": "92036", "MIMEType": "application/dicom", "FileInodeChangeDate": "2023-03-10 08:28:00", "SourceFile": "/media/harvest/domain/medical_science/dicom/series-00000/image-00014.dcm"}}]}}